pw4py/__init__.py
pw4py/alliance.py
pw4py/nation.py
pw4py/pw4py.py
PW4py-0.1.1.dist-info/LICENSE
PW4py-0.1.1.dist-info/METADATA
PW4py-0.1.1.dist-info/WHEEL
PW4py-0.1.1.dist-info/top_level.txt
PW4py-0.1.1.dist-info/RECORD
