Metadata-Version: 2.1
Name: PW4py
Version: 0.1.1
Summary: Politics & War API wrapper for Python
Home-page: https://gitlab.com/jdtech/pw4py
Author: JDTech
Author-email: UNKNOWN
License: MIT
Keywords: pnw politicsandwar
Platform: UNKNOWN
Requires-Dist: requests
